{"179":{"77":{"intensidade":"1","direcao":"4"},"86":{"intensidade":"1","direcao":"3"},"87":{"intensidade":"1","direcao":"2"},"78":{"intensidade":"1","direcao":"5"},"79":{"intensidade":"1","direcao":"5"},"80":{"intensidade":"1","direcao":"5"},"286":{"intensidade":"1","direcao":"1"},"285":{"intensidade":"1","direcao":"1"},"284":{"intensidade":"1","direcao":"1"},"283":{"intensidade":"1","direcao":"1"},"281":{"intensidade":"1","direcao":"2"},"280":{"intensidade":"1","direcao":"2"},"282":{"intensidade":"1","direcao":"2"},"279":{"intensidade":"1","direcao":"2"},"278":{"intensidade":"1","direcao":"2"},"277":{"intensidade":"1","direcao":"2"},"276":{"intensidade":"1","direcao":"3"},"275":{"intensidade":"1","direcao":"3"}},"178":{"77":{"intensidade":"1","direcao":"4"},"78":{"intensidade":"1","direcao":"4"},"79":{"intensidade":"1","direcao":"4"},"80":{"intensidade":"1","direcao":"4"},"81":{"intensidade":"1","direcao":"4"},"82":{"intensidade":"1","direcao":"4"},"83":{"intensidade":"1","direcao":"4"},"84":{"intensidade":"1","direcao":"4"},"85":{"intensidade":"1","direcao":"3"},"87":{"intensidade":"1","direcao":"2"},"86":{"intensidade":"1","direcao":"2"},"285":{"intensidade":"1","direcao":"1"},"284":{"intensidade":"1","direcao":"1"},"283":{"intensidade":"1","direcao":"1"},"282":{"intensidade":"1","direcao":"1"},"280":{"intensidade":"1","direcao":"2"},"281":{"intensidade":"1","direcao":"2"},"279":{"intensidade":"1","direcao":"2"},"278":{"intensidade":"1","direcao":"2"},"277":{"intensidade":"1","direcao":"2"},"276":{"intensidade":"1","direcao":"3"}},"177":{"77":{"intensidade":"1","direcao":"4"},"78":{"intensidade":"1","direcao":"4"},"79":{"intensidade":"1","direcao":"4"},"80":{"intensidade":"1","direcao":"4"},"81":{"intensidade":"1","direcao":"4"},"82":{"intensidade":"1","direcao":"4"},"83":{"intensidade":"1","direcao":"4"},"87":{"intensidade":"1","direcao":"2"},"86":{"intensidade":"1","direcao":"2"},"85":{"intensidade":"1","direcao":"2"},"84":{"intensidade":"1","direcao":"3"},"284":{"intensidade":"1","direcao":"1"},"283":{"intensidade":"1","direcao":"1"},"282":{"intensidade":"1","direcao":"1"},"281":{"intensidade":"1","direcao":"1"},"280":{"intensidade":"1","direcao":"2"},"279":{"intensidade":"1","direcao":"2"},"278":{"intensidade":"1","direcao":"2"},"277":{"intensidade":"1","direcao":"2"}},"176":{"77":{"intensidade":"1","direcao":"4"},"78":{"intensidade":"1","direcao":"4"},"79":{"intensidade":"1","direcao":"4"},"80":{"intensidade":"1","direcao":"4"},"81":{"intensidade":"1","direcao":"4"},"82":{"intensidade":"1","direcao":"4"},"83":{"intensidade":"1","direcao":"3"},"84":{"intensidade":"1","direcao":"2"},"87":{"intensidade":"1","direcao":"2"},"86":{"intensidade":"1","direcao":"2"},"85":{"intensidade":"1","direcao":"2"},"283":{"intensidade":"1","direcao":"1"},"282":{"intensidade":"1","direcao":"1"},"281":{"intensidade":"1","direcao":"1"},"280":{"intensidade":"1","direcao":"2"},"279":{"intensidade":"1","direcao":"2"},"278":{"intensidade":"1","direcao":"2"},"277":{"intensidade":"1","direcao":"2"}},"175":{"77":{"intensidade":"1","direcao":"4"},"78":{"intensidade":"1","direcao":"4"},"79":{"intensidade":"1","direcao":"4"},"80":{"intensidade":"1","direcao":"4"},"81":{"intensidade":"1","direcao":"4"},"82":{"intensidade":"1","direcao":"3"},"83":{"intensidade":"1","direcao":"2"},"84":{"intensidade":"1","direcao":"2"},"85":{"intensidade":"1","direcao":"2"},"86":{"intensidade":"1","direcao":"2"},"87":{"intensidade":"1","direcao":"2"},"282":{"intensidade":"1","direcao":"1"},"281":{"intensidade":"1","direcao":"1"},"280":{"intensidade":"1","direcao":"2"},"279":{"intensidade":"1","direcao":"2"},"278":{"intensidade":"1","direcao":"2"}},"174":{"77":{"intensidade":"1","direcao":"4"},"78":{"intensidade":"1","direcao":"4"},"79":{"intensidade":"1","direcao":"4"},"80":{"intensidade":"1","direcao":"4"},"81":{"intensidade":"1","direcao":"3"},"82":{"intensidade":"1","direcao":"2"},"83":{"intensidade":"1","direcao":"2"},"84":{"intensidade":"1","direcao":"2"},"85":{"intensidade":"1","direcao":"2"},"86":{"intensidade":"1","direcao":"2"},"87":{"intensidade":"1","direcao":"2"},"281":{"intensidade":"1","direcao":"1"},"280":{"intensidade":"1","direcao":"2"},"279":{"intensidade":"1","direcao":"2"}},"173":{"77":{"intensidade":"1","direcao":"4"},"78":{"intensidade":"1","direcao":"4"},"79":{"intensidade":"1","direcao":"4"},"80":{"intensidade":"1","direcao":"3"},"81":{"intensidade":"1","direcao":"2"},"87":{"intensidade":"1","direcao":"2"},"86":{"intensidade":"1","direcao":"2"},"85":{"intensidade":"1","direcao":"2"},"82":{"intensidade":"1","direcao":"2"},"83":{"intensidade":"1","direcao":"2"},"84":{"intensidade":"1","direcao":"2"},"88":{"intensidade":"1","direcao":"1"},"89":{"intensidade":"1","direcao":"0"},"90":{"intensidade":"1","direcao":"0"}},"180":{"87":{"intensidade":"1","direcao":"3"},"78":{"intensidade":"1","direcao":"5"},"77":{"intensidade":"1","direcao":"5"},"79":{"intensidade":"1","direcao":"5"},"285":{"intensidade":"1","direcao":"1"},"287":{"intensidade":"1","direcao":"1"},"286":{"intensidade":"1","direcao":"1"},"284":{"intensidade":"1","direcao":"2"},"282":{"intensidade":"1","direcao":"2"},"281":{"intensidade":"1","direcao":"2"},"280":{"intensidade":"1","direcao":"2"},"283":{"intensidade":"1","direcao":"2"},"279":{"intensidade":"1","direcao":"2"},"278":{"intensidade":"1","direcao":"2"},"277":{"intensidade":"1","direcao":"2"},"276":{"intensidade":"1","direcao":"3"},"275":{"intensidade":"1","direcao":"3"},"274":{"intensidade":"1","direcao":"3"}},"172":{"78":{"intensidade":"1","direcao":"4"},"77":{"intensidade":"1","direcao":"4"},"79":{"intensidade":"1","direcao":"3"},"87":{"intensidade":"1","direcao":"2"},"86":{"intensidade":"1","direcao":"2"},"85":{"intensidade":"1","direcao":"2"},"84":{"intensidade":"1","direcao":"2"},"83":{"intensidade":"1","direcao":"2"},"82":{"intensidade":"1","direcao":"2"},"81":{"intensidade":"1","direcao":"2"},"80":{"intensidade":"1","direcao":"2"},"89":{"intensidade":"1","direcao":"1"},"88":{"intensidade":"1","direcao":"1"},"90":{"intensidade":"1","direcao":"0"},"91":{"intensidade":"1","direcao":"0"}},"171":{"77":{"intensidade":"1","direcao":"4"},"79":{"intensidade":"1","direcao":"3"},"78":{"intensidade":"1","direcao":"3"},"89":{"intensidade":"1","direcao":"2"},"88":{"intensidade":"1","direcao":"2"},"87":{"intensidade":"1","direcao":"2"},"86":{"intensidade":"1","direcao":"2"},"85":{"intensidade":"1","direcao":"2"},"84":{"intensidade":"1","direcao":"2"},"80":{"intensidade":"1","direcao":"2"},"81":{"intensidade":"1","direcao":"2"},"82":{"intensidade":"1","direcao":"2"},"83":{"intensidade":"1","direcao":"2"}},"170":{"78":{"intensidade":"1","direcao":"3"},"77":{"intensidade":"1","direcao":"3"},"79":{"intensidade":"1","direcao":"3"},"87":{"intensidade":"1","direcao":"2"},"86":{"intensidade":"1","direcao":"2"},"85":{"intensidade":"1","direcao":"2"},"84":{"intensidade":"1","direcao":"2"},"83":{"intensidade":"1","direcao":"2"},"82":{"intensidade":"1","direcao":"2"},"81":{"intensidade":"1","direcao":"2"},"80":{"intensidade":"1","direcao":"2"}},"169":{"78":{"intensidade":"1","direcao":"3"},"79":{"intensidade":"1","direcao":"3"},"86":{"intensidade":"1","direcao":"2"},"85":{"intensidade":"1","direcao":"2"},"84":{"intensidade":"1","direcao":"2"},"83":{"intensidade":"1","direcao":"2"},"82":{"intensidade":"1","direcao":"2"},"81":{"intensidade":"1","direcao":"2"},"80":{"intensidade":"1","direcao":"2"}},"168":{"79":{"intensidade":"1","direcao":"3"},"80":{"intensidade":"1","direcao":"2"},"81":{"intensidade":"1","direcao":"2"}},"181":{"88":{"intensidade":"1","direcao":"3"},"77":{"intensidade":"1","direcao":"5"},"78":{"intensidade":"1","direcao":"5"},"284":{"intensidade":"1","direcao":"1"},"288":{"intensidade":"1","direcao":"1"},"287":{"intensidade":"1","direcao":"1"},"286":{"intensidade":"1","direcao":"1"},"282":{"intensidade":"1","direcao":"2"},"281":{"intensidade":"1","direcao":"2"},"280":{"intensidade":"1","direcao":"2"},"283":{"intensidade":"1","direcao":"2"},"279":{"intensidade":"1","direcao":"2"},"278":{"intensidade":"1","direcao":"2"},"277":{"intensidade":"1","direcao":"2"},"285":{"intensidade":"1","direcao":"0"},"276":{"intensidade":"1","direcao":"3"},"275":{"intensidade":"1","direcao":"3"}},"182":{"89":{"intensidade":"1","direcao":"3"},"283":{"intensidade":"1","direcao":"1"},"289":{"intensidade":"1","direcao":"1"},"288":{"intensidade":"1","direcao":"1"},"287":{"intensidade":"1","direcao":"1"},"286":{"intensidade":"1","direcao":"1"},"282":{"intensidade":"1","direcao":"2"},"281":{"intensidade":"1","direcao":"2"},"280":{"intensidade":"1","direcao":"2"},"279":{"intensidade":"1","direcao":"2"},"278":{"intensidade":"1","direcao":"2"},"277":{"intensidade":"1","direcao":"2"},"285":{"intensidade":"1","direcao":"0"},"284":{"intensidade":"1","direcao":"0"},"276":{"intensidade":"1","direcao":"3"}},"278":{"82":{"intensidade":"1","direcao":"3"},"81":{"intensidade":"1","direcao":"3"},"88":{"intensidade":"1","direcao":"6"},"87":{"intensidade":"1","direcao":"5"},"281":{"intensidade":"1","direcao":"7"},"280":{"intensidade":"1","direcao":"6"},"279":{"intensidade":"1","direcao":"6"},"278":{"intensidade":"1","direcao":"6"},"277":{"intensidade":"1","direcao":"6"},"276":{"intensidade":"1","direcao":"6"},"275":{"intensidade":"1","direcao":"6"},"289":{"intensidade":"1","direcao":"0"},"288":{"intensidade":"1","direcao":"0"},"287":{"intensidade":"1","direcao":"0"},"286":{"intensidade":"1","direcao":"0"},"285":{"intensidade":"1","direcao":"0"},"284":{"intensidade":"1","direcao":"0"},"283":{"intensidade":"1","direcao":"0"},"282":{"intensidade":"1","direcao":"0"}},"279":{"82":{"intensidade":"1","direcao":"3"},"81":{"intensidade":"1","direcao":"3"},"86":{"intensidade":"1","direcao":"5"},"83":{"intensidade":"1","direcao":"4"},"84":{"intensidade":"1","direcao":"4"},"85":{"intensidade":"1","direcao":"4"},"88":{"intensidade":"1","direcao":"6"},"87":{"intensidade":"1","direcao":"6"},"282":{"intensidade":"1","direcao":"7"},"281":{"intensidade":"1","direcao":"6"},"280":{"intensidade":"1","direcao":"6"},"279":{"intensidade":"1","direcao":"6"},"278":{"intensidade":"1","direcao":"6"},"277":{"intensidade":"1","direcao":"6"},"276":{"intensidade":"1","direcao":"6"},"275":{"intensidade":"1","direcao":"6"},"289":{"intensidade":"1","direcao":"0"},"288":{"intensidade":"1","direcao":"0"},"287":{"intensidade":"1","direcao":"0"},"286":{"intensidade":"1","direcao":"0"},"285":{"intensidade":"1","direcao":"0"},"284":{"intensidade":"1","direcao":"0"},"283":{"intensidade":"1","direcao":"0"}},"280":{"82":{"intensidade":"1","direcao":"3"},"81":{"intensidade":"1","direcao":"3"},"85":{"intensidade":"1","direcao":"5"},"83":{"intensidade":"1","direcao":"4"},"84":{"intensidade":"1","direcao":"4"},"86":{"intensidade":"1","direcao":"6"},"88":{"intensidade":"1","direcao":"6"},"87":{"intensidade":"1","direcao":"6"},"283":{"intensidade":"1","direcao":"7"},"289":{"intensidade":"1","direcao":"7"},"282":{"intensidade":"1","direcao":"6"},"281":{"intensidade":"1","direcao":"6"},"280":{"intensidade":"1","direcao":"6"},"279":{"intensidade":"1","direcao":"6"},"278":{"intensidade":"1","direcao":"6"},"277":{"intensidade":"1","direcao":"6"},"276":{"intensidade":"1","direcao":"6"},"275":{"intensidade":"1","direcao":"6"},"274":{"intensidade":"1","direcao":"5"},"288":{"intensidade":"1","direcao":"0"},"287":{"intensidade":"1","direcao":"0"},"286":{"intensidade":"1","direcao":"0"},"285":{"intensidade":"1","direcao":"0"},"284":{"intensidade":"1","direcao":"0"}},"281":{"82":{"intensidade":"1","direcao":"3"},"81":{"intensidade":"1","direcao":"3"},"84":{"intensidade":"1","direcao":"5"},"83":{"intensidade":"1","direcao":"4"},"86":{"intensidade":"1","direcao":"6"},"85":{"intensidade":"1","direcao":"6"},"88":{"intensidade":"1","direcao":"6"},"87":{"intensidade":"1","direcao":"6"},"284":{"intensidade":"1","direcao":"7"},"288":{"intensidade":"1","direcao":"7"},"283":{"intensidade":"1","direcao":"6"},"282":{"intensidade":"1","direcao":"6"},"281":{"intensidade":"1","direcao":"6"},"280":{"intensidade":"1","direcao":"6"},"279":{"intensidade":"1","direcao":"6"},"278":{"intensidade":"1","direcao":"6"},"277":{"intensidade":"1","direcao":"6"},"276":{"intensidade":"1","direcao":"6"},"275":{"intensidade":"1","direcao":"6"},"274":{"intensidade":"1","direcao":"5"},"273":{"intensidade":"1","direcao":"5"},"287":{"intensidade":"1","direcao":"0"},"286":{"intensidade":"1","direcao":"0"},"285":{"intensidade":"1","direcao":"0"}},"282":{"81":{"intensidade":"1","direcao":"5"},"82":{"intensidade":"1","direcao":"5"},"83":{"intensidade":"1","direcao":"5"},"84":{"intensidade":"1","direcao":"5"},"88":{"intensidade":"1","direcao":"6"},"87":{"intensidade":"1","direcao":"6"},"86":{"intensidade":"1","direcao":"6"},"85":{"intensidade":"1","direcao":"6"},"285":{"intensidade":"1","direcao":"7"},"287":{"intensidade":"1","direcao":"7"},"286":{"intensidade":"1","direcao":"7"},"284":{"intensidade":"1","direcao":"7"},"283":{"intensidade":"1","direcao":"6"},"282":{"intensidade":"1","direcao":"6"},"281":{"intensidade":"1","direcao":"6"},"280":{"intensidade":"1","direcao":"6"},"279":{"intensidade":"1","direcao":"6"},"278":{"intensidade":"1","direcao":"6"},"277":{"intensidade":"1","direcao":"6"},"276":{"intensidade":"1","direcao":"6"},"275":{"intensidade":"1","direcao":"6"},"272":{"intensidade":"1","direcao":"5"},"274":{"intensidade":"1","direcao":"5"},"273":{"intensidade":"1","direcao":"5"}},"285":{"84":{"intensidade":"1","direcao":"5"},"85":{"intensidade":"1","direcao":"7"},"88":{"intensidade":"1","direcao":"7"},"87":{"intensidade":"1","direcao":"7"},"86":{"intensidade":"1","direcao":"7"},"83":{"intensidade":"1","direcao":"5"},"284":{"intensidade":"1","direcao":"7"},"283":{"intensidade":"1","direcao":"7"},"282":{"intensidade":"1","direcao":"7"},"281":{"intensidade":"1","direcao":"7"},"280":{"intensidade":"1","direcao":"6"},"279":{"intensidade":"1","direcao":"6"},"278":{"intensidade":"1","direcao":"6"},"277":{"intensidade":"1","direcao":"6"},"276":{"intensidade":"1","direcao":"6"},"275":{"intensidade":"1","direcao":"6"},"274":{"intensidade":"1","direcao":"5"},"273":{"intensidade":"1","direcao":"5"},"272":{"intensidade":"1","direcao":"5"},"271":{"intensidade":"1","direcao":"5"},"270":{"intensidade":"1","direcao":"5"}},"283":{"82":{"intensidade":"1","direcao":"5"},"81":{"intensidade":"1","direcao":"5"},"83":{"intensidade":"1","direcao":"5"},"84":{"intensidade":"1","direcao":"5"},"88":{"intensidade":"1","direcao":"6"},"87":{"intensidade":"1","direcao":"6"},"86":{"intensidade":"1","direcao":"6"},"85":{"intensidade":"1","direcao":"6"},"286":{"intensidade":"1","direcao":"7"},"285":{"intensidade":"1","direcao":"7"},"284":{"intensidade":"1","direcao":"7"},"283":{"intensidade":"1","direcao":"7"},"282":{"intensidade":"1","direcao":"6"},"281":{"intensidade":"1","direcao":"6"},"280":{"intensidade":"1","direcao":"6"},"279":{"intensidade":"1","direcao":"6"},"278":{"intensidade":"1","direcao":"6"},"277":{"intensidade":"1","direcao":"6"},"276":{"intensidade":"1","direcao":"6"},"275":{"intensidade":"1","direcao":"6"},"271":{"intensidade":"1","direcao":"5"},"274":{"intensidade":"1","direcao":"5"},"273":{"intensidade":"1","direcao":"5"},"272":{"intensidade":"1","direcao":"5"}},"284":{"83":{"intensidade":"1","direcao":"5"},"82":{"intensidade":"1","direcao":"5"},"84":{"intensidade":"1","direcao":"5"},"85":{"intensidade":"1","direcao":"7"},"86":{"intensidade":"1","direcao":"7"},"87":{"intensidade":"1","direcao":"7"},"88":{"intensidade":"1","direcao":"7"},"285":{"intensidade":"1","direcao":"7"},"284":{"intensidade":"1","direcao":"7"},"283":{"intensidade":"1","direcao":"7"},"282":{"intensidade":"1","direcao":"7"},"281":{"intensidade":"1","direcao":"6"},"280":{"intensidade":"1","direcao":"6"},"279":{"intensidade":"1","direcao":"6"},"278":{"intensidade":"1","direcao":"6"},"277":{"intensidade":"1","direcao":"6"},"276":{"intensidade":"1","direcao":"6"},"275":{"intensidade":"1","direcao":"6"},"274":{"intensidade":"1","direcao":"5"},"273":{"intensidade":"1","direcao":"5"},"272":{"intensidade":"1","direcao":"5"},"271":{"intensidade":"1","direcao":"5"},"270":{"intensidade":"1","direcao":"5"}},"286":{"89":{"intensidade":"1","direcao":"7"},"88":{"intensidade":"1","direcao":"7"},"87":{"intensidade":"1","direcao":"7"},"86":{"intensidade":"1","direcao":"7"},"85":{"intensidade":"1","direcao":"7"},"84":{"intensidade":"1","direcao":"5"},"283":{"intensidade":"1","direcao":"7"},"282":{"intensidade":"1","direcao":"7"},"281":{"intensidade":"1","direcao":"7"},"280":{"intensidade":"1","direcao":"7"},"279":{"intensidade":"1","direcao":"6"},"278":{"intensidade":"1","direcao":"6"},"277":{"intensidade":"1","direcao":"6"},"276":{"intensidade":"1","direcao":"6"},"275":{"intensidade":"1","direcao":"6"},"274":{"intensidade":"1","direcao":"5"},"273":{"intensidade":"1","direcao":"5"},"272":{"intensidade":"1","direcao":"5"},"271":{"intensidade":"1","direcao":"5"}},"277":{"88":{"intensidade":"1","direcao":"5"},"181":{"intensidade":"1","direcao":"2"},"180":{"intensidade":"1","direcao":"2"},"179":{"intensidade":"1","direcao":"2"},"182":{"intensidade":"1","direcao":"2"},"183":{"intensidade":"1","direcao":"2"},"184":{"intensidade":"1","direcao":"2"},"178":{"intensidade":"1","direcao":"2"},"185":{"intensidade":"1","direcao":"2"},"280":{"intensidade":"1","direcao":"7"},"279":{"intensidade":"1","direcao":"6"},"278":{"intensidade":"1","direcao":"6"},"277":{"intensidade":"1","direcao":"6"},"276":{"intensidade":"1","direcao":"6"},"275":{"intensidade":"1","direcao":"6"},"289":{"intensidade":"1","direcao":"0"},"288":{"intensidade":"1","direcao":"0"},"287":{"intensidade":"1","direcao":"0"},"286":{"intensidade":"1","direcao":"0"},"285":{"intensidade":"1","direcao":"0"},"284":{"intensidade":"1","direcao":"0"},"283":{"intensidade":"1","direcao":"0"},"282":{"intensidade":"1","direcao":"0"},"281":{"intensidade":"1","direcao":"0"}},"276":{"89":{"intensidade":"1","direcao":"5"},"181":{"intensidade":"1","direcao":"2"},"279":{"intensidade":"1","direcao":"7"},"278":{"intensidade":"1","direcao":"6"},"277":{"intensidade":"1","direcao":"6"},"276":{"intensidade":"1","direcao":"6"},"275":{"intensidade":"1","direcao":"6"},"289":{"intensidade":"1","direcao":"0"},"288":{"intensidade":"1","direcao":"0"},"287":{"intensidade":"1","direcao":"0"},"286":{"intensidade":"1","direcao":"0"},"285":{"intensidade":"1","direcao":"0"},"284":{"intensidade":"1","direcao":"0"},"281":{"intensidade":"1","direcao":"0"},"280":{"intensidade":"1","direcao":"0"},"283":{"intensidade":"1","direcao":"0"},"282":{"intensidade":"1","direcao":"0"}},"275":{"90":{"intensidade":"1","direcao":"5"},"181":{"intensidade":"1","direcao":"2"},"278":{"intensidade":"1","direcao":"7"},"277":{"intensidade":"1","direcao":"6"},"276":{"intensidade":"1","direcao":"6"},"275":{"intensidade":"1","direcao":"6"},"289":{"intensidade":"1","direcao":"0"},"288":{"intensidade":"1","direcao":"0"},"287":{"intensidade":"1","direcao":"0"},"285":{"intensidade":"1","direcao":"0"},"286":{"intensidade":"1","direcao":"0"},"283":{"intensidade":"1","direcao":"0"},"284":{"intensidade":"1","direcao":"0"},"282":{"intensidade":"1","direcao":"0"},"281":{"intensidade":"1","direcao":"0"},"280":{"intensidade":"1","direcao":"0"},"279":{"intensidade":"1","direcao":"0"}},"274":{"91":{"intensidade":"1","direcao":"5"},"181":{"intensidade":"1","direcao":"2"},"277":{"intensidade":"1","direcao":"7"},"276":{"intensidade":"1","direcao":"6"},"275":{"intensidade":"1","direcao":"6"},"289":{"intensidade":"1","direcao":"0"},"285":{"intensidade":"1","direcao":"0"},"284":{"intensidade":"1","direcao":"0"},"283":{"intensidade":"1","direcao":"0"},"282":{"intensidade":"1","direcao":"0"},"281":{"intensidade":"1","direcao":"0"},"280":{"intensidade":"1","direcao":"0"},"279":{"intensidade":"1","direcao":"0"},"278":{"intensidade":"1","direcao":"0"},"288":{"intensidade":"1","direcao":"0"},"287":{"intensidade":"1","direcao":"0"},"286":{"intensidade":"1","direcao":"0"}},"273":{"92":{"intensidade":"1","direcao":"6"},"181":{"intensidade":"1","direcao":"2"},"276":{"intensidade":"1","direcao":"7"},"275":{"intensidade":"1","direcao":"6"},"289":{"intensidade":"1","direcao":"0"},"288":{"intensidade":"1","direcao":"0"},"287":{"intensidade":"1","direcao":"0"},"286":{"intensidade":"1","direcao":"0"},"285":{"intensidade":"1","direcao":"1"}},"272":{"92":{"intensidade":"1","direcao":"6"},"181":{"intensidade":"1","direcao":"2"},"275":{"intensidade":"1","direcao":"7"}},"271":{"92":{"intensidade":"1","direcao":"5"},"181":{"intensidade":"1","direcao":"2"},"274":{"intensidade":"1","direcao":"7"}},"270":{"93":{"intensidade":"1","direcao":"5"},"181":{"intensidade":"1","direcao":"2"},"273":{"intensidade":"1","direcao":"7"}},"269":{"94":{"intensidade":"1","direcao":"5"},"181":{"intensidade":"1","direcao":"2"},"272":{"intensidade":"1","direcao":"7"}},"268":{"95":{"intensidade":"1","direcao":"5"},"181":{"intensidade":"1","direcao":"2"},"271":{"intensidade":"1","direcao":"7"}},"267":{"96":{"intensidade":"1","direcao":"5"},"181":{"intensidade":"1","direcao":"2"},"268":{"intensidade":"1","direcao":"7"},"269":{"intensidade":"1","direcao":"0"},"270":{"intensidade":"1","direcao":"0"}},"266":{"97":{"intensidade":"1","direcao":"5"},"181":{"intensidade":"1","direcao":"2"},"267":{"intensidade":"1","direcao":"7"}},"265":{"98":{"intensidade":"1","direcao":"5"},"181":{"intensidade":"1","direcao":"2"},"266":{"intensidade":"1","direcao":"7"}},"264":{"99":{"intensidade":"1","direcao":"5"},"181":{"intensidade":"1","direcao":"2"},"265":{"intensidade":"1","direcao":"7"}},"263":{"100":{"intensidade":"1","direcao":"5"},"181":{"intensidade":"1","direcao":"2"},"264":{"intensidade":"1","direcao":"7"}},"262":{"101":{"intensidade":"1","direcao":"5"},"181":{"intensidade":"1","direcao":"2"},"263":{"intensidade":"1","direcao":"7"}},"261":{"102":{"intensidade":"1","direcao":"5"},"181":{"intensidade":"1","direcao":"2"},"262":{"intensidade":"1","direcao":"7"}},"260":{"103":{"intensidade":"1","direcao":"5"},"181":{"intensidade":"1","direcao":"2"},"261":{"intensidade":"1","direcao":"7"}},"259":{"104":{"intensidade":"1","direcao":"4"},"105":{"intensidade":"1","direcao":"5"},"181":{"intensidade":"1","direcao":"2"},"260":{"intensidade":"1","direcao":"7"}},"258":{"106":{"intensidade":"1","direcao":"5"},"181":{"intensidade":"1","direcao":"2"},"259":{"intensidade":"1","direcao":"7"}},"257":{"107":{"intensidade":"1","direcao":"5"},"181":{"intensidade":"1","direcao":"2"},"255":{"intensidade":"1","direcao":"7"},"256":{"intensidade":"1","direcao":"0"},"257":{"intensidade":"1","direcao":"0"},"258":{"intensidade":"1","direcao":"0"}},"256":{"108":{"intensidade":"1","direcao":"4"},"109":{"intensidade":"1","direcao":"4"},"110":{"intensidade":"1","direcao":"5"},"181":{"intensidade":"1","direcao":"2"},"254":{"intensidade":"1","direcao":"7"}},"255":{"111":{"intensidade":"1","direcao":"5"},"180":{"intensidade":"1","direcao":"3"},"253":{"intensidade":"1","direcao":"7"}},"254":{"112":{"intensidade":"1","direcao":"5"},"180":{"intensidade":"1","direcao":"2"},"252":{"intensidade":"1","direcao":"7"}},"253":{"113":{"intensidade":"1","direcao":"5"},"180":{"intensidade":"1","direcao":"2"},"247":{"intensidade":"1","direcao":"7"},"248":{"intensidade":"1","direcao":"0"},"249":{"intensidade":"1","direcao":"0"},"250":{"intensidade":"1","direcao":"0"},"251":{"intensidade":"1","direcao":"0"}},"252":{"114":{"intensidade":"1","direcao":"4"},"115":{"intensidade":"1","direcao":"4"},"116":{"intensidade":"1","direcao":"4"},"117":{"intensidade":"1","direcao":"5"},"180":{"intensidade":"1","direcao":"2"},"246":{"intensidade":"1","direcao":"7"}},"251":{"118":{"intensidade":"1","direcao":"5"},"180":{"intensidade":"1","direcao":"2"},"245":{"intensidade":"1","direcao":"7"}},"250":{"119":{"intensidade":"1","direcao":"5"},"180":{"intensidade":"1","direcao":"2"},"244":{"intensidade":"1","direcao":"7"}},"249":{"120":{"intensidade":"1","direcao":"4"},"121":{"intensidade":"1","direcao":"4"},"122":{"intensidade":"1","direcao":"4"},"123":{"intensidade":"1","direcao":"5"},"180":{"intensidade":"1","direcao":"2"},"243":{"intensidade":"1","direcao":"7"}},"248":{"124":{"intensidade":"1","direcao":"5"},"180":{"intensidade":"1","direcao":"2"},"231":{"intensidade":"1","direcao":"7"},"232":{"intensidade":"1","direcao":"0"},"233":{"intensidade":"1","direcao":"0"},"234":{"intensidade":"1","direcao":"0"},"235":{"intensidade":"1","direcao":"0"},"236":{"intensidade":"1","direcao":"0"},"237":{"intensidade":"1","direcao":"0"},"238":{"intensidade":"1","direcao":"0"},"239":{"intensidade":"1","direcao":"0"},"240":{"intensidade":"1","direcao":"0"},"241":{"intensidade":"1","direcao":"0"},"242":{"intensidade":"1","direcao":"0"}},"247":{"125":{"intensidade":"1","direcao":"5"},"180":{"intensidade":"1","direcao":"2"},"230":{"intensidade":"1","direcao":"7"}},"246":{"126":{"intensidade":"1","direcao":"5"},"179":{"intensidade":"1","direcao":"3"},"229":{"intensidade":"1","direcao":"7"}},"245":{"127":{"intensidade":"1","direcao":"4"},"128":{"intensidade":"1","direcao":"4"},"129":{"intensidade":"1","direcao":"4"},"130":{"intensidade":"1","direcao":"4"},"131":{"intensidade":"1","direcao":"4"},"132":{"intensidade":"1","direcao":"5"},"179":{"intensidade":"1","direcao":"2"},"222":{"intensidade":"1","direcao":"7"},"223":{"intensidade":"1","direcao":"0"},"224":{"intensidade":"1","direcao":"0"},"225":{"intensidade":"1","direcao":"0"},"226":{"intensidade":"1","direcao":"0"},"227":{"intensidade":"1","direcao":"0"},"228":{"intensidade":"1","direcao":"0"}},"244":{"133":{"intensidade":"1","direcao":"5"},"179":{"intensidade":"1","direcao":"2"},"221":{"intensidade":"1","direcao":"7"}},"243":{"134":{"intensidade":"1","direcao":"5"},"179":{"intensidade":"1","direcao":"2"},"220":{"intensidade":"1","direcao":"7"}},"242":{"135":{"intensidade":"1","direcao":"4"},"136":{"intensidade":"1","direcao":"4"},"137":{"intensidade":"1","direcao":"4"},"138":{"intensidade":"1","direcao":"4"},"139":{"intensidade":"1","direcao":"4"},"140":{"intensidade":"1","direcao":"5"},"179":{"intensidade":"1","direcao":"2"},"219":{"intensidade":"1","direcao":"7"}},"241":{"141":{"intensidade":"1","direcao":"5"},"179":{"intensidade":"1","direcao":"2"},"203":{"intensidade":"1","direcao":"7"},"204":{"intensidade":"1","direcao":"0"},"205":{"intensidade":"1","direcao":"0"},"206":{"intensidade":"1","direcao":"0"},"207":{"intensidade":"1","direcao":"0"},"208":{"intensidade":"1","direcao":"0"},"209":{"intensidade":"1","direcao":"0"},"210":{"intensidade":"1","direcao":"0"},"211":{"intensidade":"1","direcao":"0"},"212":{"intensidade":"1","direcao":"0"},"213":{"intensidade":"1","direcao":"0"},"214":{"intensidade":"1","direcao":"0"},"215":{"intensidade":"1","direcao":"0"},"216":{"intensidade":"1","direcao":"0"},"217":{"intensidade":"1","direcao":"0"},"218":{"intensidade":"1","direcao":"0"}},"240":{"142":{"intensidade":"1","direcao":"4"},"143":{"intensidade":"1","direcao":"4"},"144":{"intensidade":"1","direcao":"4"},"145":{"intensidade":"1","direcao":"5"},"179":{"intensidade":"1","direcao":"2"},"202":{"intensidade":"1","direcao":"7"}},"239":{"146":{"intensidade":"1","direcao":"5"},"178":{"intensidade":"1","direcao":"3"},"201":{"intensidade":"1","direcao":"7"}},"238":{"147":{"intensidade":"1","direcao":"4"},"148":{"intensidade":"1","direcao":"4"},"149":{"intensidade":"1","direcao":"4"},"150":{"intensidade":"1","direcao":"4"},"151":{"intensidade":"1","direcao":"4"},"152":{"intensidade":"1","direcao":"4"},"153":{"intensidade":"1","direcao":"4"},"154":{"intensidade":"1","direcao":"5"},"178":{"intensidade":"1","direcao":"2"},"200":{"intensidade":"1","direcao":"7"}},"237":{"155":{"intensidade":"1","direcao":"5"},"178":{"intensidade":"1","direcao":"2"},"199":{"intensidade":"1","direcao":"7"}},"236":{"156":{"intensidade":"1","direcao":"4"},"157":{"intensidade":"1","direcao":"4"},"158":{"intensidade":"1","direcao":"4"},"159":{"intensidade":"1","direcao":"5"},"177":{"intensidade":"1","direcao":"3"},"198":{"intensidade":"1","direcao":"7"}},"235":{"160":{"intensidade":"1","direcao":"5"},"176":{"intensidade":"1","direcao":"3"},"191":{"intensidade":"1","direcao":"0"},"194":{"intensidade":"1","direcao":"0"},"197":{"intensidade":"1","direcao":"0"},"196":{"intensidade":"1","direcao":"0"},"195":{"intensidade":"1","direcao":"0"},"193":{"intensidade":"1","direcao":"0"},"192":{"intensidade":"1","direcao":"0"},"190":{"intensidade":"1","direcao":"7"}},"234":{"161":{"intensidade":"1","direcao":"4"},"162":{"intensidade":"1","direcao":"4"},"163":{"intensidade":"1","direcao":"4"},"164":{"intensidade":"1","direcao":"4"},"165":{"intensidade":"1","direcao":"4"},"166":{"intensidade":"1","direcao":"4"},"167":{"intensidade":"1","direcao":"4"},"168":{"intensidade":"1","direcao":"4"},"169":{"intensidade":"1","direcao":"4"},"170":{"intensidade":"1","direcao":"4"},"171":{"intensidade":"1","direcao":"4"},"172":{"intensidade":"1","direcao":"4"},"173":{"intensidade":"1","direcao":"4"},"174":{"intensidade":"1","direcao":"4"},"175":{"intensidade":"1","direcao":"3"},"176":{"intensidade":"1","direcao":"0"},"189":{"intensidade":"1","direcao":"0"},"188":{"intensidade":"1","direcao":"0"},"187":{"intensidade":"1","direcao":"0"},"186":{"intensidade":"1","direcao":"0"},"185":{"intensidade":"1","direcao":"0"},"184":{"intensidade":"1","direcao":"0"},"183":{"intensidade":"1","direcao":"0"},"182":{"intensidade":"1","direcao":"0"},"181":{"intensidade":"1","direcao":"0"},"180":{"intensidade":"1","direcao":"0"},"179":{"intensidade":"1","direcao":"0"},"178":{"intensidade":"1","direcao":"0"},"177":{"intensidade":"1","direcao":"0"}},"233":{"174":{"intensidade":"1","direcao":"3"},"176":{"intensidade":"1","direcao":"1"}},"232":{"173":{"intensidade":"1","direcao":"3"},"177":{"intensidade":"1","direcao":"1"}},"231":{"172":{"intensidade":"1","direcao":"3"},"178":{"intensidade":"1","direcao":"1"}},"230":{"171":{"intensidade":"1","direcao":"3"},"179":{"intensidade":"1","direcao":"1"}},"229":{"170":{"intensidade":"1","direcao":"3"},"180":{"intensidade":"1","direcao":"1"}},"228":{"169":{"intensidade":"1","direcao":"3"},"181":{"intensidade":"1","direcao":"1"}},"227":{"168":{"intensidade":"1","direcao":"3"},"182":{"intensidade":"1","direcao":"1"}},"226":{"167":{"intensidade":"1","direcao":"3"},"183":{"intensidade":"1","direcao":"1"}},"225":{"166":{"intensidade":"1","direcao":"3"},"184":{"intensidade":"1","direcao":"1"}},"224":{"165":{"intensidade":"1","direcao":"3"},"185":{"intensidade":"1","direcao":"1"}},"223":{"164":{"intensidade":"1","direcao":"3"},"162":{"intensidade":"1","direcao":"4"},"163":{"intensidade":"1","direcao":"4"},"186":{"intensidade":"1","direcao":"1"},"195":{"intensidade":"1","direcao":"0"},"194":{"intensidade":"1","direcao":"0"},"193":{"intensidade":"1","direcao":"0"},"192":{"intensidade":"1","direcao":"0"},"191":{"intensidade":"1","direcao":"0"},"190":{"intensidade":"1","direcao":"0"},"189":{"intensidade":"1","direcao":"0"},"188":{"intensidade":"1","direcao":"0"},"187":{"intensidade":"1","direcao":"0"}},"222":{"161":{"intensidade":"1","direcao":"3"},"196":{"intensidade":"1","direcao":"1"}},"221":{"160":{"intensidade":"1","direcao":"3"},"159":{"intensidade":"1","direcao":"4"},"158":{"intensidade":"1","direcao":"4"},"157":{"intensidade":"1","direcao":"4"},"156":{"intensidade":"1","direcao":"4"},"155":{"intensidade":"1","direcao":"4"},"154":{"intensidade":"1","direcao":"4"},"153":{"intensidade":"1","direcao":"4"},"197":{"intensidade":"1","direcao":"1"},"198":{"intensidade":"1","direcao":"0"},"199":{"intensidade":"1","direcao":"0"},"200":{"intensidade":"1","direcao":"0"},"201":{"intensidade":"1","direcao":"0"},"202":{"intensidade":"1","direcao":"0"},"203":{"intensidade":"1","direcao":"0"}},"220":{"152":{"intensidade":"1","direcao":"3"},"151":{"intensidade":"1","direcao":"4"},"150":{"intensidade":"1","direcao":"4"},"149":{"intensidade":"1","direcao":"4"},"148":{"intensidade":"1","direcao":"4"},"147":{"intensidade":"1","direcao":"4"},"146":{"intensidade":"1","direcao":"4"},"145":{"intensidade":"1","direcao":"4"},"144":{"intensidade":"1","direcao":"4"},"204":{"intensidade":"1","direcao":"1"}},"219":{"143":{"intensidade":"1","direcao":"3"},"205":{"intensidade":"1","direcao":"1"},"206":{"intensidade":"1","direcao":"0"},"207":{"intensidade":"1","direcao":"0"},"208":{"intensidade":"1","direcao":"0"},"209":{"intensidade":"1","direcao":"0"}},"218":{"142":{"intensidade":"1","direcao":"3"},"141":{"intensidade":"1","direcao":"4"},"140":{"intensidade":"1","direcao":"4"},"139":{"intensidade":"1","direcao":"4"},"138":{"intensidade":"1","direcao":"4"},"137":{"intensidade":"1","direcao":"4"},"136":{"intensidade":"1","direcao":"4"},"135":{"intensidade":"1","direcao":"4"},"210":{"intensidade":"1","direcao":"1"}},"217":{"134":{"intensidade":"1","direcao":"3"},"211":{"intensidade":"1","direcao":"1"},"212":{"intensidade":"1","direcao":"0"},"213":{"intensidade":"1","direcao":"0"},"214":{"intensidade":"1","direcao":"0"},"215":{"intensidade":"1","direcao":"0"}},"216":{"133":{"intensidade":"1","direcao":"3"},"216":{"intensidade":"1","direcao":"1"}},"215":{"132":{"intensidade":"1","direcao":"3"},"131":{"intensidade":"1","direcao":"4"},"130":{"intensidade":"1","direcao":"4"},"129":{"intensidade":"1","direcao":"4"},"128":{"intensidade":"1","direcao":"4"},"127":{"intensidade":"1","direcao":"4"},"126":{"intensidade":"1","direcao":"4"},"217":{"intensidade":"1","direcao":"1"}},"214":{"125":{"intensidade":"1","direcao":"3"},"218":{"intensidade":"1","direcao":"1"},"219":{"intensidade":"1","direcao":"0"},"220":{"intensidade":"1","direcao":"0"},"221":{"intensidade":"1","direcao":"0"},"222":{"intensidade":"1","direcao":"0"},"223":{"intensidade":"1","direcao":"0"},"224":{"intensidade":"1","direcao":"0"}},"213":{"124":{"intensidade":"1","direcao":"3"},"225":{"intensidade":"1","direcao":"1"}},"212":{"123":{"intensidade":"1","direcao":"3"},"226":{"intensidade":"1","direcao":"1"},"227":{"intensidade":"1","direcao":"0"},"229":{"intensidade":"1","direcao":"0"},"228":{"intensidade":"1","direcao":"0"},"230":{"intensidade":"1","direcao":"0"},"231":{"intensidade":"1","direcao":"0"},"232":{"intensidade":"1","direcao":"0"},"233":{"intensidade":"1","direcao":"0"},"234":{"intensidade":"1","direcao":"0"}},"211":{"122":{"intensidade":"1","direcao":"3"},"121":{"intensidade":"1","direcao":"4"},"120":{"intensidade":"1","direcao":"4"},"119":{"intensidade":"1","direcao":"4"},"118":{"intensidade":"1","direcao":"4"},"235":{"intensidade":"1","direcao":"1"}},"210":{"117":{"intensidade":"1","direcao":"3"},"236":{"intensidade":"1","direcao":"1"}},"209":{"116":{"intensidade":"1","direcao":"3"},"237":{"intensidade":"1","direcao":"1"},"238":{"intensidade":"1","direcao":"0"},"239":{"intensidade":"1","direcao":"0"},"240":{"intensidade":"1","direcao":"0"},"241":{"intensidade":"1","direcao":"0"},"242":{"intensidade":"1","direcao":"0"}},"208":{"115":{"intensidade":"1","direcao":"3"},"243":{"intensidade":"1","direcao":"1"}},"207":{"114":{"intensidade":"1","direcao":"3"},"113":{"intensidade":"1","direcao":"4"},"112":{"intensidade":"1","direcao":"4"},"111":{"intensidade":"1","direcao":"4"},"110":{"intensidade":"1","direcao":"4"},"244":{"intensidade":"1","direcao":"1"},"245":{"intensidade":"1","direcao":"0"},"246":{"intensidade":"1","direcao":"0"},"247":{"intensidade":"1","direcao":"0"},"248":{"intensidade":"1","direcao":"0"}},"206":{"109":{"intensidade":"1","direcao":"3"},"249":{"intensidade":"1","direcao":"1"}},"205":{"108":{"intensidade":"1","direcao":"3"},"250":{"intensidade":"1","direcao":"1"}},"204":{"107":{"intensidade":"1","direcao":"3"},"251":{"intensidade":"1","direcao":"1"}},"203":{"106":{"intensidade":"1","direcao":"3"},"252":{"intensidade":"1","direcao":"1"}},"202":{"105":{"intensidade":"1","direcao":"3"},"253":{"intensidade":"1","direcao":"1"}},"201":{"104":{"intensidade":"1","direcao":"3"},"254":{"intensidade":"1","direcao":"1"}},"200":{"103":{"intensidade":"1","direcao":"3"},"255":{"intensidade":"1","direcao":"1"},"256":{"intensidade":"1","direcao":"0"},"257":{"intensidade":"1","direcao":"0"},"258":{"intensidade":"1","direcao":"0"}},"199":{"102":{"intensidade":"1","direcao":"3"},"259":{"intensidade":"1","direcao":"1"}},"198":{"101":{"intensidade":"1","direcao":"3"},"260":{"intensidade":"1","direcao":"1"},"261":{"intensidade":"1","direcao":"0"},"262":{"intensidade":"1","direcao":"0"},"263":{"intensidade":"1","direcao":"0"}},"195":{"98":{"intensidade":"1","direcao":"3"},"266":{"intensidade":"1","direcao":"1"}},"196":{"99":{"intensidade":"1","direcao":"3"},"265":{"intensidade":"1","direcao":"1"}},"194":{"97":{"intensidade":"1","direcao":"3"},"267":{"intensidade":"1","direcao":"1"}},"197":{"100":{"intensidade":"1","direcao":"3"},"264":{"intensidade":"1","direcao":"1"}},"193":{"96":{"intensidade":"1","direcao":"3"},"268":{"intensidade":"1","direcao":"1"}},"192":{"95":{"intensidade":"1","direcao":"3"},"269":{"intensidade":"1","direcao":"1"}},"191":{"94":{"intensidade":"1","direcao":"3"},"270":{"intensidade":"1","direcao":"1"},"286":{"intensidade":"1","direcao":"7"},"285":{"intensidade":"1","direcao":"7"}},"190":{"93":{"intensidade":"1","direcao":"3"},"271":{"intensidade":"1","direcao":"1"},"272":{"intensidade":"1","direcao":"0"},"274":{"intensidade":"1","direcao":"0"},"273":{"intensidade":"1","direcao":"0"},"275":{"intensidade":"1","direcao":"0"},"286":{"intensidade":"1","direcao":"7"},"285":{"intensidade":"1","direcao":"7"},"284":{"intensidade":"1","direcao":"7"}},"189":{"92":{"intensidade":"1","direcao":"3"},"276":{"intensidade":"1","direcao":"1"},"287":{"intensidade":"1","direcao":"7"},"283":{"intensidade":"1","direcao":"7"},"286":{"intensidade":"1","direcao":"7"},"285":{"intensidade":"1","direcao":"7"},"284":{"intensidade":"1","direcao":"7"}},"184":{"91":{"intensidade":"1","direcao":"2"},"281":{"intensidade":"1","direcao":"1"},"291":{"intensidade":"1","direcao":"1"},"290":{"intensidade":"1","direcao":"1"},"289":{"intensidade":"1","direcao":"1"},"288":{"intensidade":"1","direcao":"1"},"280":{"intensidade":"1","direcao":"2"},"279":{"intensidade":"1","direcao":"2"},"278":{"intensidade":"1","direcao":"2"},"277":{"intensidade":"1","direcao":"2"},"287":{"intensidade":"1","direcao":"0"},"286":{"intensidade":"1","direcao":"0"},"285":{"intensidade":"1","direcao":"0"},"284":{"intensidade":"1","direcao":"0"},"283":{"intensidade":"1","direcao":"0"},"282":{"intensidade":"1","direcao":"0"}},"185":{"91":{"intensidade":"1","direcao":"2"},"280":{"intensidade":"1","direcao":"1"},"279":{"intensidade":"1","direcao":"2"},"278":{"intensidade":"1","direcao":"2"},"277":{"intensidade":"1","direcao":"2"},"287":{"intensidade":"1","direcao":"0"},"286":{"intensidade":"1","direcao":"0"},"285":{"intensidade":"1","direcao":"0"},"291":{"intensidade":"1","direcao":"0"},"290":{"intensidade":"1","direcao":"0"},"289":{"intensidade":"1","direcao":"0"},"288":{"intensidade":"1","direcao":"0"},"284":{"intensidade":"1","direcao":"0"},"283":{"intensidade":"1","direcao":"0"},"282":{"intensidade":"1","direcao":"0"},"281":{"intensidade":"1","direcao":"0"}},"186":{"91":{"intensidade":"1","direcao":"2"},"279":{"intensidade":"1","direcao":"1"},"278":{"intensidade":"1","direcao":"2"},"277":{"intensidade":"1","direcao":"2"},"290":{"intensidade":"1","direcao":"0"},"289":{"intensidade":"1","direcao":"0"},"288":{"intensidade":"1","direcao":"0"},"287":{"intensidade":"1","direcao":"0"},"286":{"intensidade":"1","direcao":"0"},"285":{"intensidade":"1","direcao":"0"},"284":{"intensidade":"1","direcao":"0"},"283":{"intensidade":"1","direcao":"0"},"282":{"intensidade":"1","direcao":"0"},"281":{"intensidade":"1","direcao":"0"},"280":{"intensidade":"1","direcao":"0"}},"187":{"91":{"intensidade":"1","direcao":"2"},"278":{"intensidade":"1","direcao":"1"},"277":{"intensidade":"1","direcao":"2"},"289":{"intensidade":"1","direcao":"0"},"287":{"intensidade":"1","direcao":"0"},"286":{"intensidade":"1","direcao":"0"},"288":{"intensidade":"1","direcao":"0"},"285":{"intensidade":"1","direcao":"0"},"284":{"intensidade":"1","direcao":"0"},"283":{"intensidade":"1","direcao":"0"},"282":{"intensidade":"1","direcao":"0"},"281":{"intensidade":"1","direcao":"0"},"279":{"intensidade":"1","direcao":"0"},"280":{"intensidade":"1","direcao":"0"}},"188":{"91":{"intensidade":"1","direcao":"3"},"288":{"intensidade":"1","direcao":"0"},"287":{"intensidade":"1","direcao":"0"},"286":{"intensidade":"1","direcao":"0"},"285":{"intensidade":"1","direcao":"0"},"284":{"intensidade":"1","direcao":"0"},"283":{"intensidade":"1","direcao":"0"},"282":{"intensidade":"1","direcao":"0"},"281":{"intensidade":"1","direcao":"0"},"280":{"intensidade":"1","direcao":"0"},"279":{"intensidade":"1","direcao":"0"},"278":{"intensidade":"1","direcao":"0"},"277":{"intensidade":"1","direcao":"1"}},"183":{"90":{"intensidade":"1","direcao":"3"},"282":{"intensidade":"1","direcao":"1"},"290":{"intensidade":"1","direcao":"1"},"289":{"intensidade":"1","direcao":"1"},"288":{"intensidade":"1","direcao":"1"},"287":{"intensidade":"1","direcao":"1"},"281":{"intensidade":"1","direcao":"2"},"280":{"intensidade":"1","direcao":"2"},"279":{"intensidade":"1","direcao":"2"},"278":{"intensidade":"1","direcao":"2"},"277":{"intensidade":"1","direcao":"2"},"285":{"intensidade":"1","direcao":"0"},"286":{"intensidade":"1","direcao":"0"},"284":{"intensidade":"1","direcao":"0"},"283":{"intensidade":"1","direcao":"0"}},"287":{"282":{"intensidade":"1","direcao":"7"},"281":{"intensidade":"1","direcao":"7"},"280":{"intensidade":"1","direcao":"7"},"279":{"intensidade":"1","direcao":"6"},"278":{"intensidade":"1","direcao":"6"},"277":{"intensidade":"1","direcao":"6"},"276":{"intensidade":"1","direcao":"6"},"275":{"intensidade":"1","direcao":"6"},"274":{"intensidade":"1","direcao":"5"},"273":{"intensidade":"1","direcao":"5"},"272":{"intensidade":"1","direcao":"5"}},"288":{"281":{"intensidade":"1","direcao":"7"},"280":{"intensidade":"1","direcao":"7"},"279":{"intensidade":"1","direcao":"6"},"278":{"intensidade":"1","direcao":"6"},"277":{"intensidade":"1","direcao":"6"},"276":{"intensidade":"1","direcao":"6"},"275":{"intensidade":"1","direcao":"6"},"274":{"intensidade":"1","direcao":"5"},"273":{"intensidade":"1","direcao":"5"}},"289":{"280":{"intensidade":"1","direcao":"7"},"278":{"intensidade":"1","direcao":"6"},"279":{"intensidade":"1","direcao":"6"},"277":{"intensidade":"1","direcao":"6"},"276":{"intensidade":"1","direcao":"6"},"275":{"intensidade":"1","direcao":"6"},"274":{"intensidade":"1","direcao":"5"}},"290":{"279":{"intensidade":"1","direcao":"7"},"278":{"intensidade":"1","direcao":"6"},"277":{"intensidade":"1","direcao":"6"},"276":{"intensidade":"1","direcao":"6"}},"291":[]}